pymf4/__init__.py
pymf4/main.py
tests/__init__.py
tests/test_main.py
pymf4-0.1.0.dist-info/METADATA
pymf4-0.1.0.dist-info/WHEEL
pymf4-0.1.0.dist-info/top_level.txt
pymf4-0.1.0.dist-info/RECORD
