Metadata-Version: 2.2
Name: pymf4
Version: 0.1.0
Summary: A Python project named pymf4
Requires-Python: >=3.9.0
Provides-Extra: dev
Requires-Dist: ruff; extra == "dev"
Requires-Dist: pytest; extra == "dev"
